MANIFEST.in
README.md
setup.cfg
setup.py
BSG/__init__.py
BSG/__main__.py
BSG/core.py
BSG/default.json
BSG.egg-info/PKG-INFO
BSG.egg-info/SOURCES.txt
BSG.egg-info/dependency_links.txt
BSG.egg-info/entry_points.txt
BSG.egg-info/top_level.txt
BSG/NMSL/.BSDBID
BSG/NMSL/after.json
BSG/NMSL/before.json
BSG/NMSL/bosh.json
BSG/NMSL/famous.json