Metadata-Version: 1.2
Name: BSG
Version: 0.1
Summary: Modulized version of BullshitGenerator. Original version see https://github.com/menzi11/BullshitGenerator
Home-page: https://github.com/mvfki/BullshitGenerator
Author: mvfki
License: UNKNOWN
Platform: UNKNOWN
Requires-Python: >=3.4
